[
  {
    "id": "1",
    "weeks": "1",
    "subject": "Accounting",
    "class": "SS1",
    "term": "First term",
    "topics": "Introduction to financial accounting Meaning of book keeping -meaning of financial accounting -differences between book keeping and financial accounting Importance of accounting",
    "learningObjectives": [
      {
        "id": "1",
        "value": "Introduction to financial accounting Meaning of book keeping -meaning of financial accounting -differences between book keeping and financial accounting Importance of accounting"
      },
      {
        "id": "2",
        "value": ""
      },
      {
        "id": "3",
        "value": ""
      },
      {
        "id": "4",
        "value": ""
      }
    ],
    "learningActivities": [
      {
        "id": "1",
        "value": "-students as a class explain what book keeping and accounting is -students in small groups draw up similarities and differences of book keeping and accounting with the group leader to present -students in pairs analyse and share the importance of financial accounting -whole class to visit this link for history of accounting ; "
      },
      {
        "id": "2",
        "value": ""
      },
      {
        "id": "3",
        "value": ""
      },
      {
        "id": "4",
        "value": ""
      }
    ],
    "embeddedCoreSkills": [
      {
        "id": "1",
        "value": "-collaboration and communication -critical thinking and problem solving -leadership and personal development -digital literacy"
      },
      {
        "id": "2",
        "value": ""
      },
      {
        "id": "3",
        "value": ""
      },
      {
        "id": "4",
        "value": ""
      }
    ],
    "learningResources": [
      {
        "id": "1",
        "value": "Audio-visual resources Flash cards ; Web resources "
      },
      {
        "id": "2",
        "value": "https://www.topbookeepingcourse/"
      },
      {
        "id": "3",
        "value": "https://courses.ju,enleaming.com/"
      },
      {
        "id": "4",
        "value": ""
      }
    ]
  },
  {
    "id": "2",
    "weeks": "2",
    "subject": "Accounting",
    "class": "SS1",
    "term": "First term",
    "topics": "History of Accounting worldwide and Nigeria users of accounting information -internal and external users and their needs of accounting information",
    "learninObjectives": [
      {
        "id": "1",
        "value": "By the end of the lesson, students should be able to: ; narrate the emergence of accounting worldwide and Nigeria specifically enumerate the beneficiaries of accounting information identify the needs of both internal and external users; ;"
      },
      {
        "id": "2",
        "value": ""
      },
      {
        "id": "3",
        "value": ""
      },
      {
        "id": "4",
        "value": ""
      }
    ],
    "learningActivities": [
      {
        "id": "1",
        "value": "-students; to present in small groups, he present evolution of accounting worldwide and in Nigeria -students as a class discuss the beneficiaries of accounting information -students in pairs explain the qualities of a good accounting information ;"
      },
      {
        "id": "2",
        "value": ""
      },
      {
        "id": "3",
        "value": ""
      },
      {
        "id": "4",
        "value": ""
      }
    ],
    "embeddedCoreSkills": [
      {
        "id": "1",
        "value": "-Critical thinking and problem solving -Collaboration and Communication -leadership and personal development"
      },
      {
        "id": "2",
        "value": ""
      },
      {
        "id": "3",
        "value": ""
      },
      {
        "id": "4",
        "value": ""
      }
    ],
    "learningResources": [
      {
        "id": "1",
        "value": "Web resources "
      },
      {
        "id": "2",
        "value": "https://en.m.wikipedia/"
      },
      {
        "id": "3",
        "value": ""
      },
      {
        "id": "4",
        "value": ""
      }
    ]
  },
  {
    "id": "3",
    "weeks": "3",
    "subject": "Accounting",
    "class": "SS1",
    "term": "First term",
    "topics": "Advantages and limitations of accounting –accounting process cycle -identify and analyzing business transactions and events -recording in the journals -posting to the ledger Extraction of trial balance Preparation of financial statements",
    "learningObjectives": [
      {
        "id": "1",
        "value": "By the end of the lesson, students should be able to"
      },
      {
        "id": "2",
        "value": "I] recapitulate the features of Accounting information"
      },
      {
        "id": "3",
        "value": " Ii] explain the accounting process cycle in correct order"
      },
      {
        "id": "4",
        "value": ":  Iv] justify the order of accounting process cycle"
      }
    ],
    "learningActivities": [
      {
        "id": "1",
        "value": "-students in small groups presentations groups A: merits and demerits of accounting Group B: analyse accounting process cycle Group C: explain extraction of trial balance from ledger balances -students in pairs to explain accounting cycle"
      },
      {
        "id": "2",
        "value": ""
      },
      {
        "id": "3",
        "value": ""
      },
      {
        "id": "4",
        "value": ""
      }
    ],
    "embeddedCoreSkills": [
      {
        "id": "1",
        "value": "-Critical thinking and problem solving -Collaboration and Communication -leadership and personal development"
      },
      {
        "id": "2",
        "value": ""
      },
      {
        "id": "3",
        "value": ""
      },
      {
        "id": "4",
        "value": ""
      }
    ],
    "learningResources": [
      {
        "id": "1",
        "value": "Audio –visual Resources Accounting process charts Posters on accounting process cycle Concept mapping of accounting process cycle  Web Resources "
      },
      {
        "id": "2",
        "value": "https://www.investopedia.com/"
      },
      {
        "id": "3",
        "value": ""
      },
      {
        "id": "4",
        "value": ""
      }
    ]
  },
  {
    "id": "4",
    "weeks": "4",
    "subject": "Accounting",
    "class": "SS1",
    "term": "First term",
    "topics": "Career opportunities in book keeping and accounting Accounting professional bodies Accounting professional ethnics ",
    "learningObjectives": [
      {
        "id": "1",
        "value": "By the end of the lesson, students should be able to:"
      },
      {
        "id": "2",
        "value": " I] list out current opportunities in book keeping and accounting "
      },
      {
        "id": "3",
        "value": "Ii] mention professional bodies regulating accounting profession in Nigeria"
      },
      {
        "id": "4",
        "value": ""
      }
    ],
    "learningActivities": [
      {
        "id": "1",
        "value": "Mention their future careers -students in pairs mention accounting professional bodies in Nigeria and outside Nigeria -students in small group mention qualities of a good accountant "
      },
      {
        "id": "2",
        "value": ""
      },
      {
        "id": "3",
        "value": ""
      },
      {
        "id": "4",
        "value": ""
      }
    ],
    "embeddedCoreSkills": [
      {
        "id": "1",
        "value": "Communications -critical thinking and problem solving -leadership and personal development"
      },
      {
        "id": "2",
        "value": ""
      },
      {
        "id": "3",
        "value": ""
      },
      {
        "id": "4",
        "value": ""
      }
    ],
    "learningResources": [
      {
        "id": "1",
        "value": "Resources Magazines cuttings on pictures of professionals in business sector  Web Resources Wwww.allacounting.careers.com  "
      },
      {
        "id": "2",
        "value": "https://www.ifac.org/"
      },
      {
        "id": "3",
        "value": ""
      },
      {
        "id": "4",
        "value": ""
      }
    ]
  },
  {
    "id": "5",
    "weeks": "5",
    "subject": "Accounting",
    "class": "SS1",
    "term": "First term",
    "topics": "Accounting equation and double entry -purpose and functions of source documents -introduction to subsidiary books Meaning of subsidiary books, types of subsidiary books",
    "learningObjectives": [
      {
        "id": "1",
        "value": "By the end of the lesson, students should be able to: I]state original accounting equation and reorganize it Ii] identify and apply the double entry principle in posting business transaction Iii] paraphrase the meaning of source document"
      },
      {
        "id": "2",
        "value": ""
      },
      {
        "id": "3",
        "value": ""
      },
      {
        "id": "4",
        "value": ""
      }
    ],
    "learningActivities": [
      {
        "id": "1",
        "value": "-students in small groups mention assets and facilities of a business -students in pairs explain the meaning and functions of source documents Students as a class explain the meaning of subsidiary books and give the types of subsidiary books"
      },
      {
        "id": "2",
        "value": ""
      },
      {
        "id": "3",
        "value": ""
      },
      {
        "id": "4",
        "value": ""
      }
    ],
    "embeddedCoreSkills": [
      {
        "id": "1",
        "value": "Critical thinking and problem solving -communication and collaboration &nbsp; Leadership and personal development"
      },
      {
        "id": "2",
        "value": ""
      },
      {
        "id": "3",
        "value": ""
      },
      {
        "id": "4",
        "value": ""
      }
    ],
    "learningResources": [
      {
        "id": "1",
        "value": "Audio-visual resources Receipt, invoice, cheque, stub, vouchers, pay-in-slip, teller, bank statement &nbsp; Web Resources "
      },
      {
        "id": "2",
        "value": "https://www.edunote.com/"
      },
      {
        "id": "3",
        "value": ""
      },
      {
        "id": "4",
        "value": ""
      }
    ]
  },
  {
    "id": "6",
    "weeks": "6",
    "subject": "Accounting",
    "class": "SS1",
    "term": "First term",
    "topics": "Sales journal and purchases&nbsp;&nbsp; journals return inwards journals and return outwards journal Cash book",
    "learningObjectives": [
      {
        "id": "1",
        "value": "By the end of the lesson, students should be able to: I] outline various sources documents Ii] prepare sales and purchases day books Iii] post transactions into return inward and return outward journals"
      },
      {
        "id": "2",
        "value": ""
      },
      {
        "id": "3",
        "value": ""
      },
      {
        "id": "4",
        "value": ""
      }
    ],
    "learningActivities": [
      {
        "id": "1",
        "value": "Individual students bring samples of cheque leaves Invoice , receipts, pay in slip, withdrawal slip, point of sales machine ATM card etc Students in small groups, discuss the uses of source documents brought by the students -students as a class post entries into sales and purchases day books"
      },
      {
        "id": "2",
        "value": ""
      },
      {
        "id": "3",
        "value": ""
      },
      {
        "id": "4",
        "value": ""
      }
    ],
    "embeddedCoreSkills": [
      {
        "id": "1",
        "value": "-critical thinking and problem solving -digital literacy -leadership and personal development"
      },
      {
        "id": "2",
        "value": ""
      },
      {
        "id": "3",
        "value": ""
      },
      {
        "id": "4",
        "value": ""
      }
    ],
    "learningResources": [
      {
        "id": "1",
        "value": "Audio-visual resources Format of the journals and cash book Illustrate&nbsp; questions and real objects Using Excel to draw the formats Real objects such as cheque leaves, invoice , receipts, withdrawal slip, ATM machine and POS machine &nbsp; Web resources "
      },
      {
        "id": "2",
        "value": "https://corpoeratefinancieinstitute.com/"
      },
      {
        "id": "3",
        "value": ""
      },
      {
        "id": "4",
        "value": ""
      }
    ]
  },
  {
    "id": "7",
    "weeks": "7",
    "subject": "Accounting",
    "class": "SS1",
    "term": "First term",
    "topics": "",
    "Status": "Mid term Break"
  },
  {
    "id": "8",
    "weeks": "8",
    "subject": "Accounting",
    "class": "SS1",
    "term": "First term",
    "topics": "Working exercises on sales journal and return inwards journal -working exercises on purchases journal and return outward journals",
    "learningObjectives": [
      {
        "id": "1",
        "value": "By the end of the lesson, students should be able to: I] solve problems on subsidiary books of account Ii] explain the meaning and types of discounts Iii] calculate the trade discount on the journal"
      },
      {
        "id": "2",
        "value": ""
      },
      {
        "id": "3",
        "value": ""
      },
      {
        "id": "4",
        "value": ""
      }
    ],
    "learningActivities": [
      {
        "id": "1",
        "value": "-students in small groups, identify various subsidiary books -students as a class post transactions to various subsidiary books -students in pairs to explain discounts and types &nbsp;"
      },
      {
        "id": "2",
        "value": ""
      },
      {
        "id": "3",
        "value": ""
      },
      {
        "id": "4",
        "value": ""
      }
    ],
    "embeddedCoreSkills": [
      {
        "id": "1",
        "value": "collaboration and communication -critical thinking and problem solving -leadership and personal development &nbsp;"
      },
      {
        "id": "2",
        "value": ""
      },
      {
        "id": "3",
        "value": ""
      },
      {
        "id": "4",
        "value": ""
      }
    ],
    "learningResources": [
      {
        "id": "1",
        "value": "Audio-visual&nbsp; resources Real sales journal Illustrative questions Charts YouTube, accounting Instruction/bean Counter using Excel to prepare journal"
      },
      {
        "id": "2",
        "value": ""
      },
      {
        "id": "3",
        "value": ""
      },
      {
        "id": "4",
        "value": ""
      }
    ]
  },
  {
    "id": "9",
    "weeks": "9",
    "subject": "Accounting",
    "class": "SS1",
    "term": "First term",
    "topics": "The ledger classifications&nbsp; of accounts Cash book-meaning and types Single column cash book",
    "learningObjectives": [
      {
        "id": "1",
        "value": "By the end of the lesson, students should be able to: I] use concept mapping to classify ledges into personal, impersonal and private Ii] define cash book Iii] identify the types of cash book Iv] explain the use of each column cash book"
      },
      {
        "id": "2",
        "value": ""
      },
      {
        "id": "3",
        "value": ""
      },
      {
        "id": "4",
        "value": ""
      }
    ],
    "learningActivities": [
      {
        "id": "1",
        "value": "-students in small groups , classify ledgers with adequate examples -students in pairs define cash book and the types -students as a class work exercise on single column cash book"
      },
      {
        "id": "2",
        "value": ""
      },
      {
        "id": "3",
        "value": ""
      },
      {
        "id": "4",
        "value": ""
      }
    ],
    "embeddedCoreSkills": [
      {
        "id": "1",
        "value": "collaboration and communication -critical thinking and problem solving -digital literacy"
      },
      {
        "id": "2",
        "value": ""
      },
      {
        "id": "3",
        "value": ""
      },
      {
        "id": "4",
        "value": ""
      }
    ],
    "learningResources": [
      {
        "id": "1",
        "value": "Audio-visual Resources Diagram showing the&nbsp; classification of ledgers Real cash book Improvise cash book &nbsp; Web Resources "
      },
      {
        "id": "2",
        "value": "https://www.wallstreetmojo.com/"
      },
      {
        "id": "3",
        "value": ""
      },
      {
        "id": "4",
        "value": ""
      }
    ]
  },
  {
    "id": "10",
    "weeks": "10",
    "subject": "Accounting",
    "class": "SS1",
    "term": "First term",
    "topics": "Cash book-double column cash book",
    "learningObjectives": [
      {
        "id": "1",
        "value": "By the end of the lesson, students should be able to: I] define cash book Ii] identify the format of double column cash book Iii] explain contra entries Iv] prepare double&nbsp; column cash book"
      },
      {
        "id": "2",
        "value": ""
      },
      {
        "id": "3",
        "value": ""
      },
      {
        "id": "4",
        "value": ""
      }
    ],
    "learningActivities": [
      {
        "id": "1",
        "value": "-students in small groups display lodgments and withdrawal of cash from bank -students in pairs prepare double column cash book -students as a class balance up the two column cash book"
      },
      {
        "id": "2",
        "value": ""
      },
      {
        "id": "3",
        "value": ""
      },
      {
        "id": "4",
        "value": ""
      }
    ],
    "embeddedCoreSkills": [
      {
        "id": "1",
        "value": "Critical thinking and problem solving -Collaboration and Communication Digital literacy -leadership and personal development"
      },
      {
        "id": "2",
        "value": ""
      },
      {
        "id": "3",
        "value": ""
      },
      {
        "id": "4",
        "value": ""
      }
    ],
    "learningResources": [
      {
        "id": "1",
        "value": "Audio-visual resources Cash book, cheque leaves &nbsp; Web resources "
      },
      {
        "id": "2",
        "value": "https://www.wallstreetmojo.com/"
      },
      {
        "id": "3",
        "value": ""
      },
      {
        "id": "4",
        "value": ""
      }
    ]
  },
  {
    "id": "11",
    "weeks": "11",
    "subject": "Accounting",
    "class": "SS1",
    "term": "First term",
    "topics": "Discounts-meaning Types, reasons for granting discount -calculation of discounts",
    "learningObjectives": [
      {
        "id": "1",
        "value": "By the end of the lesson, students should be able to: I]&nbsp; explain the term discounts , identify the types of discounts , state the features of each types , justify the reasons for granting discounts Calculate discounts granted on a transaction"
      },
      {
        "id": "2",
        "value": ""
      },
      {
        "id": "3",
        "value": ""
      },
      {
        "id": "4",
        "value": ""
      }
    ],
    "learningActivities": [
      {
        "id": "1",
        "value": "-students as a class explain the meaning and types of discounts -students in pairs to justify the reasons for discounts -students as a class calculate discounts"
      },
      {
        "id": "2",
        "value": ""
      },
      {
        "id": "3",
        "value": ""
      },
      {
        "id": "4",
        "value": ""
      }
    ],
    "embeddedCoreSkills": [
      {
        "id": "1",
        "value": "-critical thinking and problem solving -Digital literacy -leadership&nbsp; and personal development"
      },
      {
        "id": "2",
        "value": ""
      },
      {
        "id": "3",
        "value": ""
      },
      {
        "id": "4",
        "value": ""
      }
    ],
    "learningResources": [
      {
        "id": "1",
        "value": "Audio-Visual&nbsp; Resources Flash&nbsp; cards, graphs A sample question &nbsp; Web&nbsp; resources "
      },
      {
        "id": "2",
        "value": "https://www.accountingbooks.com/"
      },
      {
        "id": "3",
        "value": ""
      },
      {
        "id": "4",
        "value": ""
      }
    ]
  },
  {
    "id": "12",
    "weeks": "12",
    "subject": "Accounting",
    "class": "SS1",
    "term": "First term",
    "topics": "",
    "Status": "REVISION"
  },
  {
    "id": "13",
    "weeks": "13",
    "subject": "Accounting",
    "class": "SS1",
    "term": "First term",
    "topics": "",
    "Status": "EXAMINATION"
  }
]
