[
  {
    "_id": "1",
    "Weeks": "1",
    "Subject": "Office Practice",
    "Class": "SS1",
    "Term": "Third Term",
    "Topics": [
      {
        "id": "1",
        "value": "REVISION/WELCOME TEST"
      },
      {
        "id": "2",
        "value": ""
      },
      {
        "id": "3",
        "value": ""
      },
      {
        "id": "4",
        "value": ""
      }
    ],
    "Learning Objects": [
      {
        "id": "1",
        "value": "By the end of the lesson students should be able to recall and summarize the last term topics."
      },
      {
        "id": "2",
        "value": ""
      },
      {
        "id": "3",
        "value": ""
      },
      {
        "id": "4",
        "value": ""
      }
    ],
    "Learning Activities": [
      {
        "id": "1",
        "value": "i. Students as a class some of the last terms topics. "
      },
      {
        "id": "2",
        "value": "ii. Students in whole attempt some set questions to evaluate achievement so far."
      },
      {
        "id": "3",
        "value": ""
      },
      {
        "id": "4",
        "value": ""
      }
    ],
    "Embedded Core Skills": [
      {
        "id": "1",
        "value": "Collaboration and communication, critical thinking and problems solving leadership and personal development."
      },
      {
        "id": "2",
        "value": ""
      },
      {
        "id": "3",
        "value": ""
      },
      {
        "id": "4",
        "value": ""
      }
    ],
    "Learning Resources": [
      {
        "id": "1",
        "value": "Audio Visual Resources Set of evaluation questions"
      },
      {
        "id": "2",
        "value": ""
      },
      {
        "id": "3",
        "value": ""
      },
      {
        "id": "4",
        "value": ""
      }
    ]
  },
  {
    "_id": "2",
    "Weeks": "2",
    "Subject": "Office Practice",
    "Class": "SS1",
    "Term": "Third Term",
    "Topics": [
      {
        "id": "1",
        "value": "COMMUNICATION:Meaning,– Types (Oral, Written Non-verbal, Visual Electronic)process (sender message medium decoder) Importance of communication in an office."
      },
      {
        "id": "2",
        "value": "– Barriers to effective communication."
      },
      {
        "id": "3",
        "value": ""
      },
      {
        "id": "4",
        "value": ""
      }
    ],
    "Learning Objects": [
      {
        "id": "1",
        "value": "i. explain the term Communication with the various types "
      },
      {
        "id": "2",
        "value": "ii. analyze communication process and effective communication process."
      },
      {
        "id": "3",
        "value": "iii. justify the importance of communication in the office and society at large "
      },
      {
        "id": "4",
        "value": ""
      }
    ],
    "Learning Activities": [
      {
        "id": "1",
        "value": "i. Whole class brainstorm on the meaning and various types of Communication. "
      },
      {
        "id": "2",
        "value": "ii Students small groups deliberate on their various Communicator process "
      },
      {
        "id": "3",
        "value": "iii interpreted the message passed, and identify the barriers to effective communication and communication channel."
      },
      {
        "id": "4",
        "value": ""
      }
    ],
    "Embedded Core Skills": [
      {
        "id": "1",
        "value": "Collaboration and communication, critical thinking and problems solving leadership and personal development."
      },
      {
        "id": "2",
        "value": ""
      },
      {
        "id": "3",
        "value": ""
      },
      {
        "id": "4",
        "value": ""
      }
    ],
    "Learning Resources": [
      {
        "id": "1",
        "value": "Audio Visual Resources :Short drama presentation on effective, importance and barriers to communication"
      },
      {
        "id": "2",
        "value": "Web Resources"
      },
      {
        "id": "3",
        "value": "Video clips:<a href=https://youtu.be/RkebtEk2zUO target=_blank rel=noopener>https://youtu.be/RkebtEk2zUO</a> <a href=https://youtu.be/RkebtEk2zUO target=_blank rel=noopener>https://youtu.be/RkebtEk2zUO</a> <a href=https://youtu.be/DqpbdCoY target=_blank rel=noopener>https://youtu.be/DqpbdCoY</a>"
      },
      {
        "id": "4",
        "value": ""
      }
    ]
  },
  {
    "_id": "3",
    "Weeks": "3",
    "Subject": "Office Practice",
    "Class": "SS1",
    "Term": "Third Term",
    "Topics": [
      {
        "id": "1",
        "value": "POST OFFICE:-meaning,-services rendered,"
      },
      {
        "id": "2",
        "value": "i. Postal Services Letter: Ordinary, Registered, Express mail, Special mail, Poster restante, Telegrams."
      },
      {
        "id": "3",
        "value": "ii. Remittance:(Postal Order, Money Order."
      },
      {
        "id": "4",
        "value": "iii. Other Services (Delivery of Letter and parcels, e. t. c.-Field trip to Post Office. "
      }
    ],
    "Learning Objects": [
      {
        "id": "1",
        "value": "i. describe a Post Office with the functions,"
      },
      {
        "id": "2",
        "value": "ii. explain the services rendered by Post Office iii-evaluate the relevance of the office to the society at large. "
      },
      {
        "id": "3",
        "value": ""
      },
      {
        "id": "4",
        "value": ""
      }
    ],
    "Learning Activities": [
      {
        "id": "1",
        "value": "i. Students, as a class, visit a nearby post office."
      },
      {
        "id": "2",
        "value": "ii. Students in small groups, deliberates on their various observations from the visit."
      },
      {
        "id": "3",
        "value": "iii. Students in pairs illustrate their observations in a chart play card and share with the class. "
      },
      {
        "id": "4",
        "value": ""
      }
    ],
    "Embedded Core Skills": [
      {
        "id": "1",
        "value": "Collaboration and communication, critical thinking and problems solving leadership and personal development."
      },
      {
        "id": "2",
        "value": ""
      },
      {
        "id": "3",
        "value": ""
      },
      {
        "id": "4",
        "value": ""
      }
    ],
    "Learning Resources": [
      {
        "id": "1",
        "value": "Audio visual resources:samples of Poster Services, Remittance, Trip to Post Office (Practical)"
      },
      {
        "id": "2",
        "value": "Web resources: video clips; <a href=https://youtu.be/eakZGrVIEE target=_blank rel=noopener>https://youtu.be/eakZGrVIEE</a> <a href=https://youtube/eVlARvNd808 target=_blank>https://youtube/eVlARvNd808</a>  https://brainly.in&gt;question. "
      },
      {
        "id": "3",
        "value": ""
      },
      {
        "id": "4",
        "value": ""
      }
    ]
  },
  {
    "_id": "4",
    "Weeks": "4",
    "Subject": "Office Practice",
    "Class": "SS1",
    "Term": "Third Term",
    "Topics": [
      {
        "id": "1",
        "value": "BUSINESS ORGANISATION.Sole Proprietorship:Meaning, "
      },
      {
        "id": "2",
        "value": "– features and sources of capital."
      },
      {
        "id": "3",
        "value": "-Advantages and disadvantages."
      },
      {
        "id": "4",
        "value": ""
      }
    ],
    "Learning Objects": [
      {
        "id": "1",
        "value": "i. define Sole Proprietorship business"
      },
      {
        "id": "2",
        "value": " ii. describe the features of Sole Proprietorship business;"
      },
      {
        "id": "3",
        "value": " iii appraise the advantages and disadvantages of a Sole Proprietorship business"
      },
      {
        "id": "4",
        "value": ""
      }
    ],
    "Learning Activities": [
      {
        "id": "1",
        "value": "i. Students in small groups discuss the meaning of sole proprietorship business,"
      },
      {
        "id": "2",
        "value": " ii. Students in pairs identify the characteristics and examples of a sole proprietorship business in their community"
      },
      {
        "id": "3",
        "value": "iii. Students, as a class suggests sources of capital for a sole proprietorship business."
      },
      {
        "id": "4",
        "value": ""
      }
    ],
    "Embedded Core Skills": [
      {
        "id": "1",
        "value": "Citizenship,&nbsp; communication and collaboration students leadership and personal development "
      },
      {
        "id": "2",
        "value": ""
      },
      {
        "id": "3",
        "value": ""
      },
      {
        "id": "4",
        "value": ""
      }
    ],
    "Learning Resources": [
      {
        "id": "1",
        "value": "Audio visual resources: pictures of some familiar examples of a sole proprietorship business (e.g. tailoring, salons, ‘shoes makers, etc)"
      },
      {
        "id": "2",
        "value": "Web sites:https://www.toppr.com&gt;guides&gt;sole….., https://byjus.com&gt;commerce&gt;sole."
      },
      {
        "id": "3",
        "value": ""
      },
      {
        "id": "4",
        "value": ""
      }
    ]
  },
  {
    "_id": "5",
    "Weeks": "5",
    "Subject": "Office Practice",
    "Class": "SS1",
    "Term": "Third Term",
    "Topics": [
      {
        "id": "1",
        "value": "PARTNERSHIP "
      },
      {
        "id": "2",
        "value": "1: -Meaning, Features and Sources of Capital."
      },
      {
        "id": "3",
        "value": "– Types of Partnership – Types of Partners. – Formation of partnership."
      },
      {
        "id": "4",
        "value": "– Dissolution of a partnership. – Advantages and disadvantages"
      }
    ],
    "Learning Objects": [
      {
        "id": "1",
        "value": "By the end of the lesson, Students should be able to: – analyze the concept of partnership business.  "
      },
      {
        "id": "2",
        "value": "– Identity the features and various types of a partnership business"
      },
      {
        "id": "3",
        "value": "-justify the advantages and disadvantages of a partnership business."
      },
      {
        "id": "4",
        "value": ""
      }
    ],
    "Learning Activities": [
      {
        "id": "1",
        "value": "i. Students in whole class deliberate on possible meanings attributes and type of partnership business."
      },
      {
        "id": "2",
        "value": "ii. Students in small groups demonstrates how a partnership business is formed and dissolved "
      },
      {
        "id": "3",
        "value": "iii. Justify reasons for dissolution of partnership iv. Appraise the benefits and downside of"
      },
      {
        "id": "4",
        "value": ""
      }
    ],
    "Embedded Core Skills": [
      {
        "id": "1",
        "value": "communication and collaboration critical thinking and problem solving, students"
      },
      {
        "id": "2",
        "value": "leadership and personal development "
      },
      {
        "id": "3",
        "value": ""
      },
      {
        "id": "4",
        "value": ""
      }
    ],
    "Learning Resources": [
      {
        "id": "1",
        "value": "Audio visual resources: pictures/calendar of some partnership companies. "
      },
      {
        "id": "2",
        "value": "Web resources: Web links: https://www.investopedia.com&gt;terms <a href=https://pariotsoftware.com target=_blank rel=noopener>https://pariotsoftware.com</a> <a href=http://www.informdirect.co.uk target=_blank rel=noopener>www.informdirect.co.uk</a>"
      },
      {
        "id": "3",
        "value": ""
      },
      {
        "id": "4",
        "value": ""
      }
    ]
  },
  {
    "_id": "6",
    "Weeks": "6",
    "Subject": "Office Practice",
    "Class": "SS1",
    "Term": "Third Term",
    "Topics": [
      {
        "id": "1",
        "value": "LIMITED LIABILITY COMPANY "
      },
      {
        "id": "2",
        "value": " – Meaning of a COMPANY"
      },
      {
        "id": "3",
        "value": "-Meaning of a company Limited Liability Company: Terms used in Limited Liability; Company. (Memorandum of Association, Articles of Association, Prospective, Shares, Debentures, etc., -Dissolution of a limited liability company."
      },
      {
        "id": "4",
        "value": ""
      }
    ],
    "Learning Objects": [
      {
        "id": "1",
        "value": "By the end of the lesson, Students should be able to: i. Define a Limited Liability&nbsp; Company. ; . "
      },
      {
        "id": "2",
        "value": " ii. Explain the terms used in a Limited Liability; Company."
      },
      {
        "id": "3",
        "value": "iii. Justify reasons for dissolution of Limited Liability; Company"
      },
      {
        "id": "4",
        "value": ""
      }
    ],
    "Learning Activities": [
      {
        "id": "1",
        "value": "i. Whole class brainstorm on meaning of Limited liability Companies "
      },
      {
        "id": "2",
        "value": "ii. Differentiate the terms used in a Limited Liability Company "
      },
      {
        "id": "3",
        "value": "iii. Criticize reasons for dissolving a Limited Liability Company."
      },
      {
        "id": "4",
        "value": ""
      }
    ],
    "Embedded Core Skills": [
      {
        "id": "1",
        "value": "Critical thinking and problem solving, communication and collaboration personal development "
      },
      {
        "id": "2",
        "value": ""
      },
      {
        "id": "3",
        "value": ""
      },
      {
        "id": "4",
        "value": ""
      }
    ],
    "Learning Resources": [
      {
        "id": "1",
        "value": "Audio visual resources samples of memorandum of Association, Article of Associations etc., "
      },
      {
        "id": "2",
        "value": "Web resources web links: https://study.com&gt;academy&gt;lessons https://www.incfile.com&gt;glossary;https://law,jrank.orgpages&gt;limit.. "
      },
      {
        "id": "3",
        "value": ""
      },
      {
        "id": "4",
        "value": ""
      }
    ]
  },
  {
    "_id": "7",
    "Weeks": "7",
    "Subject": "Office Practice",
    "Class": "SS1",
    "Term": "Third Term",
    "Topics": "",
    "Status": "Mid Term Break"
  },
  {
    "_id": "8",
    "Weeks": "8",
    "Subject": "Office Practice",
    "Class": "SS1",
    "Term": "Third Term",
    "Topics": [
      {
        "id": "1",
        "value": "CO-OPERATIVE SOCIETY"
      },
      {
        "id": "2",
        "value": "-Meaning and Origin"
      },
      {
        "id": "3",
        "value": "– Types of Co-operative Societies. – Sources of Capital."
      },
      {
        "id": "4",
        "value": ""
      }
    ],
    "Learning Objects": [
      {
        "id": "1",
        "value": "-explain the meaning and origin of a cooperative society"
      },
      {
        "id": "2",
        "value": "– Identify types of Co-operative Societies,"
      },
      {
        "id": "3",
        "value": "– justify the importance of a co-operative societies"
      },
      {
        "id": "4",
        "value": ""
      }
    ],
    "Learning Activities": [
      {
        "id": "1",
        "value": "i. Students as a class discuss the possible meaning of cooperative society.;"
      },
      {
        "id": "2",
        "value": " ii. students in pairs outline and explain types of cooperative society."
      },
      {
        "id": "3",
        "value": "iii. suggests sources of capital for Co-operative Societies."
      },
      {
        "id": "4",
        "value": ""
      }
    ],
    "Embedded Core Skills": [
      {
        "id": "1",
        "value": "Critical thinking and problem solving, communication and collaboration personal development"
      },
      {
        "id": "2",
        "value": ""
      },
      {
        "id": "3",
        "value": ""
      },
      {
        "id": "4",
        "value": ""
      }
    ],
    "Learning Resources": [
      {
        "id": "1",
        "value": "Web links:https://culturalsurvival.org-publications/cultural-survival-quarterly/co-operatives-short-history  <a href=https://www/quora.com/what-are-co-operative-society target=_blank>https://www/quora.com/what-are-co-operative-society</a>"
      },
      {
        "id": "2",
        "value": ""
      },
      {
        "id": "3",
        "value": ""
      },
      {
        "id": "4",
        "value": ""
      }
    ]
  },
  {
    "_id": "9",
    "Weeks": "9",
    "Subject": "Office Practice",
    "Class": "SS1",
    "Term": "Third Term",
    "Topics": [
      {
        "id": "1",
        "value": "PUBLIC ENTERPRISES"
      },
      {
        "id": "2",
        "value": "-Meaning"
      },
      {
        "id": "3",
        "value": "-Reasons for establishing,"
      },
      {
        "id": "4",
        "value": "-Structure of public enterprises,"
      },
      {
        "id": "5",
        "value": "Differences between Public and Private Enterprises.Advantages and disadvantages of public and private enterprises."
      }
    ],
    "Learning Objects": [
      {
        "id": "1",
        "value": "By the end of the lesson, students should be able to:-define Public and Private Enterprises,"
      },
      {
        "id": "2",
        "value": "-justify the reasons for establishing Public Enterprises"
      },
      {
        "id": "3",
        "value": "– contrast Public and Private Enterprises with their advantages and disadvantages."
      },
      {
        "id": "4",
        "value": ""
      }
    ],
    "Learning Activities": [
      {
        "id": "1",
        "value": "i. Students as a class brainstorm on the definition of public and private enterprises., Enumerate the advantages and disadvantages."
      },
      {
        "id": "2",
        "value": " ii. Assess reasons for the establishment and differences between Public and Private Enterprises "
      },
      {
        "id": "3",
        "value": "Enumerate the advantages and disadvantages."
      },
      {
        "id": "4",
        "value": ""
      }
    ],
    "Embedded Core Skills": [
      {
        "id": "1",
        "value": "Communication and collaboration, critical thinking, and digital literacy skills, &nbsp;"
      },
      {
        "id": "2",
        "value": ""
      },
      {
        "id": "3",
        "value": ""
      },
      {
        "id": "4",
        "value": ""
      }
    ],
    "Learning Resources": [
      {
        "id": "1",
        "value": "Picture/charts e.g. Public and private school, Hospital, web links: nigerianinfopedia.com.ng/public-corporations-in-Nigeria https:/twww.britannica.com/topic/public-enterprise."
      },
      {
        "id": "2",
        "value": ""
      },
      {
        "id": "3",
        "value": ""
      },
      {
        "id": "4",
        "value": ""
      }
    ]
  },
  {
    "_id": "10",
    "Weeks": "10",
    "Subject": "Office Practice",
    "Class": "SS1",
    "Term": "Third Term",
    "Topics": [
      {
        "id": "1",
        "value": ""
      },
      {
        "id": "2",
        "value": ""
      },
      {
        "id": "3",
        "value": ""
      },
      {
        "id": "4",
        "value": ""
      }
    ],
    "Learning Objects": [
      {
        "id": "1",
        "value": ""
      },
      {
        "id": "2",
        "value": ""
      },
      {
        "id": "3",
        "value": ""
      },
      {
        "id": "4",
        "value": ""
      }
    ],
    "Learning Activities": [
      {
        "id": "1",
        "value": ""
      },
      {
        "id": "2",
        "value": ""
      },
      {
        "id": "3",
        "value": ""
      },
      {
        "id": "4",
        "value": ""
      }
    ],
    "Embedded Core Skills": [
      {
        "id": "1",
        "value": ""
      },
      {
        "id": "2",
        "value": ""
      },
      {
        "id": "3",
        "value": ""
      },
      {
        "id": "4",
        "value": ""
      }
    ],
    "Learning Resources": [
      {
        "id": "1",
        "value": ""
      },
      {
        "id": "2",
        "value": ""
      },
      {
        "id": "3",
        "value": ""
      },
      {
        "id": "4",
        "value": ""
      }
    ]
  },
  {
    "_id": "11",
    "Weeks": "11",
    "Subject": "Office Practice",
    "Class": "SS1",
    "Term": "Third Term",
    "Topics": [
      {
        "id": "1",
        "value": ""
      },
      {
        "id": "2",
        "value": ""
      },
      {
        "id": "3",
        "value": ""
      },
      {
        "id": "4",
        "value": ""
      }
    ],
    "Learning Objects": [
      {
        "id": "1",
        "value": ""
      },
      {
        "id": "2",
        "value": ""
      },
      {
        "id": "3",
        "value": ""
      },
      {
        "id": "4",
        "value": ""
      }
    ],
    "Learning Activities": [
      {
        "id": "1",
        "value": ""
      },
      {
        "id": "2",
        "value": ""
      },
      {
        "id": "3",
        "value": ""
      },
      {
        "id": "4",
        "value": ""
      }
    ],
    "Embedded Core Skills": [
      {
        "id": "1",
        "value": ""
      },
      {
        "id": "2",
        "value": ""
      },
      {
        "id": "3",
        "value": ""
      },
      {
        "id": "4",
        "value": ""
      }
    ],
    "Learning Resources": [
      {
        "id": "1",
        "value": ""
      },
      {
        "id": "2",
        "value": ""
      },
      {
        "id": "3",
        "value": ""
      },
      {
        "id": "4",
        "value": ""
      }
    ]
  },
  {
    "_id": "12",
    "Weeks": "12",
    "Subject": "Office Practice",
    "Class": "SS1",
    "Term": "Third Term",
    "Topics": "",
    "Status": "REVISION"
  },
  {
    "_id": "13",
    "Weeks": "13",
    "Subject": "Office Practice",
    "Class": "SS1",
    "Term": "Third Term",
    "Topics": "",
    "Status": "EXAMINATION"
  }
]
